psql_optimizer/__init__.py
psql_optimizer/management/__init__.py
psql_optimizer/management/commands/__init__.py
psql_optimizer/management/commands/func.py
psql_optimizer/management/commands/optimize_statistics.py
psql_optimizer/management/commands/set_statistics.py
psql_optimizer/management/query/__init__.py
psql_optimizer/management/query/analyze_model.py
psql_optimizer/management/query/find_table.py
psql_optimizer/management/query/set_stats.py
psql_stat_optimizer-0.0.45.dist-info/LICENSE
psql_stat_optimizer-0.0.45.dist-info/METADATA
psql_stat_optimizer-0.0.45.dist-info/WHEEL
psql_stat_optimizer-0.0.45.dist-info/top_level.txt
psql_stat_optimizer-0.0.45.dist-info/RECORD
