Metadata-Version: 2.1
Name: psql-stat-optimizer
Version: 0.0.45
Summary: Postgresql Set Statistics
Home-page: https://github.com/miare-ir/psql-optimizer
Author: Amir Alaghmandan
Author-email: amir.amotlagh@gmail.com
Classifier: License :: OSI Approved :: MIT License
Classifier: Programming Language :: Python
Classifier: Programming Language :: Python :: 3.5
Classifier: Programming Language :: Python :: 3.6
Classifier: Programming Language :: Python :: 3.7
Classifier: Programming Language :: Python :: 3.8
Classifier: Programming Language :: Python :: 3.9
Classifier: Programming Language :: Python :: 3.10
Classifier: Framework :: Django
Classifier: Framework :: Django :: 2.2
Classifier: Framework :: Django :: 3.0
Classifier: Framework :: Django :: 3.1
Classifier: Framework :: Django :: 3.2
Classifier: Framework :: Django :: 4.0
License-File: LICENSE
Requires-Dist: django-tqdm (==1.3.1)
Requires-Dist: Django (>=2.2)
